simulation_classes/Chance.py
simulation_classes/CommunityChest.py
simulation_classes/FreeParking.py
simulation_classes/Go.py
simulation_classes/GoToJail.py
simulation_classes/Jail.py
simulation_classes/MonopolyBoard.py
simulation_classes/Player.py
simulation_classes/RandomStrategy.py
simulation_classes/Station.py
simulation_classes/Strategy.py
simulation_classes/Street.py
simulation_classes/Tax.py
simulation_classes/Utility.py
simulation_classes/__init__.py
simulation_classes_catherineannie13-0.0.1.dist-info/LICENSE
simulation_classes_catherineannie13-0.0.1.dist-info/METADATA
simulation_classes_catherineannie13-0.0.1.dist-info/WHEEL
simulation_classes_catherineannie13-0.0.1.dist-info/top_level.txt
simulation_classes_catherineannie13-0.0.1.dist-info/RECORD
